opendp/network/__init__.py
opendp/network/odometer.py
opendp/network/odometer_manual.py
opendp/network/odometer_reconstruction.py
opendp/network/odometer_stochastic.py
opendp/network/layers/__init__.py
opendp/network/layers/attention.py
opendp/network/layers/bahdanau.py
opendp/network/layers/lstm.py
opendp_pytorch-0.1.0.dist-info/LICENSE
opendp_pytorch-0.1.0.dist-info/METADATA
opendp_pytorch-0.1.0.dist-info/WHEEL
opendp_pytorch-0.1.0.dist-info/top_level.txt
opendp_pytorch-0.1.0.dist-info/RECORD
