Metadata-Version: 2.1
Name: opendp-pytorch
Version: 0.1.0
Summary: PyTorch integration for the OpenDP Library
Home-page: https://opendp.org
Author: The OpenDP Project
Author-email: info@opendp.org
License: UNKNOWN
Project-URL: Source, https://github.com/opendp/opendp-pytorch
Project-URL: Issues, https://github.com/opendp/opendp-pytorch/issues
Project-URL: Documentation, https://docs.opendp.org/
Keywords: differential privacy
Platform: UNKNOWN
Classifier: Programming Language :: Python :: 3
Classifier: License :: OSI Approved :: MIT License
Classifier: Operating System :: OS Independent
Requires-Python: >=3.6
Requires-Dist: opendp
Requires-Dist: torch
Requires-Dist: torchcsprng
